TP ISL/verilog.v
module pedagio (
    input  wire E1,
    input  wire E0,
    input  wire [3:0] P,
    output reg  [6:0] seg
);

    wire peso_le_12, peso_gt_12;
    wire C1, C2, C3, ERR;

    // Comparadores
    assign peso_gt_12 = P[3] & P[2] & (P[1] | P[0]);
    assign peso_le_12 = (~P[3]) | (~P[2]) | ((~P[1]) & (~P[0]));

    // Lógica das categorias
    assign C1 = (~P[3]) & (~E1) & (~E0);   // Carro
    assign C2 = peso_le_12 & (~E1) & E0;   // Caminhonete
    assign C3 = peso_gt_12 & E1;           // Caminhão
    assign ERR = ~(C1 | C2 | C3);          // Erro

    // Decodificador 7 segmentos (common cathode)
    always @(*) begin
        if (C1)      seg = 7'b0110000; // “1”
        else if (C2) seg = 7'b1101101; // “2”
        else if (C3) seg = 7'b1111001; // “3”
        else         seg = 7'b1001111; // “E”
    end
endmodule

TP ISL/tb_pedagio.v
`timescale 1ns/1ps
module tb_pedagio;
    // Entradas (reg porque vamos alterar no tempo)
    reg E1;
    reg E0;
    reg [3:0] P;
    // Saída (wire porque vem do módulo)
    wire [6:0] seg;

    reg [6:0] temp;
    // Instancia o módulo a ser testado
    // Liga as entradas no modulo do verilog.v
    pedagio uut (
        .E1(E1),
        .E0(E0),
        .P(P),
        .seg(seg)
    );
    // Bloco inicial de simulação
    initial begin
        temp = 0;
        $dumpfile("pedagio.vcd");
        $dumpvars(0, tb_pedagio);
        
        // Mostra cabeçalho no console
        //$display("Tempo | E1 E0 P | seg");

        // Mostra sempre que mudar algo
        //$monitor("%4t | %b  %b  %b | %b", $time, E1, E0, P, seg);

        // Define valores iniciais
        E1 = 0; E0 = 0; P = 4'b0000;

        // Teste 1
        /*#10 E1 = 0; E0 = 0; P = 4'b0001;  // Exemplo 1
        #10 E1 = 0; E0 = 1; P = 4'b0110;  // Exemplo 2
        #10 E1 = 1; E0 = 0; P = 4'b1010;  // Exemplo 3
        #10 E1 = 1; E0 = 1; P = 4'b1111;  // Exemplo 4

        #10 $finish; // Encerra simulação*/

    end

    always @(*) begin
        while (temp<64) begin
            E1 = temp[5];
            E0 = temp[4];
            P = temp[3:0];
            #5
            $display("%4dns|%b%b|%b|%b|%d",$time,E1,E0,P,seg,temp);
            temp = temp + 1;         
        end
    end

endmodule

TP ISL/pedagio.vcd
$date
	Fri Oct 17 13:55:28 2025
$end
$version
	Icarus Verilog
$end
$timescale
	1ps
$end
$scope module tb_pedagio $end
$var wire 7 ! seg [6:0] $end
$var reg 1 " E0 $end
$var reg 1 # E1 $end
$var reg 4 $ P [3:0] $end
$var reg 7 % temp [6:0] $end
$scope module uut $end
$var wire 1 & C1 $end
$var wire 1 ' C2 $end
$var wire 1 ( C3 $end
$var wire 1 " E0 $end
$var wire 1 # E1 $end
$var wire 1 ) ERR $end
$var wire 4 * P [3:0] $end
$var wire 1 + peso_gt_12 $end
$var wire 1 , peso_le_12 $end
$var reg 7 - seg [6:0] $end
$upscope $end
$upscope $end
$enddefinitions $end
$comment Show the parameter values. $end
$dumpall
$end
#0
$dumpvars
b110000 -
1,
0+
b0 *
0)
0(
0'
1&
b0 %
b0 $
0#
0"
b110000 !
$end
#5000
b1 $
b1 *
b1 %
#10000
b10 $
b10 *
b10 %
#15000
b11 $
b11 *
b11 %
#20000
b100 $
b100 *
b100 %
#25000
b101 $
b101 *
b101 %
#30000
b110 $
b110 *
b110 %
#35000
b111 $
b111 *
b111 %
#40000
1)
b1001111 !
b1001111 -
0&
b1000 $
b1000 *
b1000 %
#45000
b1001 $
b1001 *
b1001 %
#50000
b1010 $
b1010 *
b1010 %
#55000
b1011 $
b1011 *
b1011 %
#60000
b1100 $
b1100 *
b1100 %
#65000
0,
1+
b1101 $
b1101 *
b1101 %
#70000
b1110 $
b1110 *
b1110 %
#75000
b1111 $
b1111 *
b1111 %
#80000
0)
b1101101 !
b1101101 -
1'
1,
0+
b0 $
b0 *
1"
b10000 %
#85000
b1 $
b1 *
b10001 %
#90000
b10 $
b10 *
b10010 %
#95000
b11 $
b11 *
b10011 %
#100000
b100 $
b100 *
b10100 %
#105000
b101 $
b101 *
b10101 %
#110000
b110 $
b110 *
b10110 %
#115000
b111 $
b111 *
b10111 %
#120000
b1000 $
b1000 *
b11000 %
#125000
b1001 $
b1001 *
b11001 %
#130000
b1010 $
b1010 *
b11010 %
#135000
b1011 $
b1011 *
b11011 %
#140000
b1100 $
b1100 *
b11100 %
#145000
1)
b1001111 !
b1001111 -
0'
0,
1+
b1101 $
b1101 *
b11101 %
#150000
b1110 $
b1110 *
b11110 %
#155000
b1111 $
b1111 *
b11111 %
#160000
1,
0+
1)
b1001111 !
b1001111 -
0(
b0 $
b0 *
0"
1#
b100000 %
#165000
b1 $
b1 *
b100001 %
#170000
b10 $
b10 *
b100010 %
#175000
b11 $
b11 *
b100011 %
#180000
b100 $
b100 *
b100100 %
#185000
b101 $
b101 *
b100101 %
#190000
b110 $
b110 *
b100110 %
#195000
b111 $
b111 *
b100111 %
#200000
b1000 $
b1000 *
b101000 %
#205000
b1001 $
b1001 *
b101001 %
#210000
b1010 $
b1010 *
b101010 %
#215000
b1011 $
b1011 *
b101011 %
#220000
b1100 $
b1100 *
b101100 %
#225000
0)
b1111001 !
b1111001 -
1(
0,
1+
b1101 $
b1101 *
b101101 %
#230000
b1110 $
b1110 *
b101110 %
#235000
b1111 $
b1111 *
b101111 %
#240000
1)
b1001111 !
b1001111 -
0(
1,
0+
b0 $
b0 *
1"
b110000 %
#245000
b1 $
b1 *
b110001 %
#250000
b10 $
b10 *
b110010 %
#255000
b11 $
b11 *
b110011 %
#260000
b100 $
b100 *
b110100 %
#265000
b101 $
b101 *
b110101 %
#270000
b110 $
b110 *
b110110 %
#275000
b111 $
b111 *
b110111 %
#280000
b1000 $
b1000 *
b111000 %
#285000
b1001 $
b1001 *
b111001 %
#290000
b1010 $
b1010 *
b111010 %
#295000
b1011 $
b1011 *
b111011 %
#300000
b1100 $
b1100 *
b111100 %
#305000
0)
b1111001 !
b1111001 -
1(
0,
1+
b1101 $
b1101 *
b111101 %
#310000
b1110 $
b1110 *
b111110 %
#315000
b1111 $
b1111 *
b111111 %
#320000
b1000000 %
